DataQC
