Metadata-Version: 1.1
Name: DataQC
Version: 0.0.104
Summary: Data quality checker.
Home-page: UNKNOWN
Author: Md Ismail Hossain
Author-email: mdismail.hossain@student.nmt.edu
License: MIT
Keywords: Data QC
Platform: UNKNOWN
Classifier: Development Status :: 5 - Production/Stable
Classifier: Intended Audience :: Education
Classifier: Operating System :: Microsoft :: Windows :: Windows 10
Classifier: License :: OSI Approved :: MIT License
Classifier: Programming Language :: Python :: 3
